cas_metadata_tools/EXIF_constants.py
cas_metadata_tools/__init__.py
cas_metadata_tools/base_constants.py
cas_metadata_tools/metadata_tools_main.py
cas_metadata_tools-1.0.1.dist-info/METADATA
cas_metadata_tools-1.0.1.dist-info/WHEEL
cas_metadata_tools-1.0.1.dist-info/licenses/LICENSE
cas_metadata_tools-1.0.1.dist-info/RECORD
